cdnjs/__init__.py
cdnjs/settings.py
cdnjs/templatetags/__init__.py
cdnjs/templatetags/cdnjstag.py
cdnjs-1.4.dist-info/LICENSE
cdnjs-1.4.dist-info/METADATA
cdnjs-1.4.dist-info/WHEEL
cdnjs-1.4.dist-info/top_level.txt
cdnjs-1.4.dist-info/RECORD
