Metadata-Version: 2.1
Name: cdnjs
Version: 1.4
Summary: CDNJS API Django Template tag, which allows to simply use cdns.
Home-page: https://gitlab.com/geany.been/django-cdnjs
Author: Maxym Papezhuk
Author-email: cods.max@gmail.com
License: UNKNOWN
Platform: UNKNOWN
Classifier: Framework :: Django
Requires-Dist: django
Requires-Dist: fuzzywuzzy[speedup]
Requires-Dist: requests
